tccm_model/__init__.py
tccm_model/tccm_model.py
tccm_model/jsonld/tccm_model.context.jsonld
tccm_model/jsonld/tccm_model.model.context.jsonld
tccm_model/jsonschema/tccm_model.schema.json
tccm_model/model/schema/tccm_model.yaml
tccm_model-0.1.3.dev12.data/data/tccm_model/model/schema/tccm_model.yaml
tccm_model-0.1.3.dev12.dist-info/AUTHORS
tccm_model-0.1.3.dev12.dist-info/METADATA
tccm_model-0.1.3.dev12.dist-info/WHEEL
tccm_model-0.1.3.dev12.dist-info/pbr.json
tccm_model-0.1.3.dev12.dist-info/top_level.txt
tccm_model-0.1.3.dev12.dist-info/RECORD
