Metadata-Version: 2.1
Name: tccm-model
Version: 0.1.3.dev12
Summary: A really nice model
Home-page: https://HOT-Ecosystem.github.io/tccm_model
Author: Dazhi Jiao
Author-email: djiao@jhu.edu
License: CC0 1.0 Universal
Keywords: linkml,LOD,Modeling,Linked open data,model
Platform: UNKNOWN
Classifier: Development Status :: 4 - Beta
Classifier: Environment :: Console
Classifier: Intended Audience :: Developers
Classifier: Intended Audience :: Science/Research
Classifier: Intended Audience :: Information Technology
Classifier: License :: CC0 1.0 Universal (CC0 1.0) Public Domain Dedication
Classifier: Programming Language :: Python :: 3 :: Only
Classifier: Programming Language :: Python :: 3.7
Classifier: Programming Language :: Python :: 3.8
Classifier: Programming Language :: Python :: 3.9
Requires-Python: >=3.7
License-File: AUTHORS
Requires-Dist: linkml-runtime (>=1.0.3,~=1.0)
